{"nodes": [{"id": "home_khuzaymah_desktop_gym_pass_pro_gym_pass_pro_mobile_lib_features_subscription_presentation_welcome_page_dart", "label": "welcome_page.dart", "file_type": "code", "source_file": "mobile/lib/features/subscription/presentation/welcome_page.dart", "source_location": null}, {"id": "presentation_welcome_page_welcomepage", "label": "WelcomePage", "file_type": "code", "source_file": "mobile/lib/features/subscription/presentation/welcome_page.dart", "source_location": null}, {"id": "consumerwidget", "label": "ConsumerWidget", "file_type": "code", "source_file": null, "source_location": null}, {"id": "subscriptionprovider", "label": "subscriptionProvider", "file_type": "code", "source_file": null, "source_location": null}, {"id": "presentation_welcome_page_tiername", "label": "_tierName", "file_type": "code", "source_file": "mobile/lib/features/subscription/presentation/welcome_page.dart", "source_location": null}, {"id": "presentation_welcome_page_build", "label": "build", "file_type": "code", "source_file": "mobile/lib/features/subscription/presentation/welcome_page.dart", "source_location": null}, {"id": "route_explore", "label": "Route /explore", "file_type": "concept", "source_file": null, "source_location": null}, {"id": "route_home", "label": "Route /home", "file_type": "concept", "source_file": null, "source_location": null}, {"id": "package_flutter_material_dart", "label": "package:flutter/material.dart", "file_type": "code", "source_file": null, "source_location": null}, {"id": "package_flutter_riverpod_flutter_riverpod_dart", "label": "package:flutter_riverpod/flutter_riverpod.dart", "file_type": "code", "source_file": null, "source_location": null}, {"id": "package_go_router_go_router_dart", "label": "package:go_router/go_router.dart", "file_type": "code", "source_file": null, "source_location": null}, {"id": "core_theme_gp_text_dart", "label": "../../../core/theme/gp_text.dart", "file_type": "code", "source_file": null, "source_location": null}, {"id": "core_theme_gp_tokens_dart", "label": "../../../core/theme/gp_tokens.dart", "file_type": "code", "source_file": null, "source_location": null}, {"id": "core_widgets_glow_dart", "label": "../../../core/widgets/glow.dart", "file_type": "code", "source_file": null, "source_location": null}, {"id": "core_widgets_overline_dart", "label": "../../../core/widgets/overline.dart", "file_type": "code", "source_file": null, "source_location": null}, {"id": "core_widgets_pill_button_dart", "label": "../../../core/widgets/pill_button.dart", "file_type": "code", "source_file": null, "source_location": null}, {"id": "l10n_app_localizations_dart", "label": "../../../l10n/app_localizations.dart", "file_type": "code", "source_file": null, "source_location": null}, {"id": "data_subscription_state_dart", "label": "../data/subscription_state.dart", "file_type": "code", "source_file": null, "source_location": null}], "edges": [{"source": "home_khuzaymah_desktop_gym_pass_pro_gym_pass_pro_mobile_lib_features_subscription_presentation_welcome_page_dart", "target": "presentation_welcome_page_welcomepage", "relation": "defines", "confidence": "EXTRACTED", "confidence_score": 1.0, "source_file": "mobile/lib/features/subscription/presentation/welcome_page.dart", "source_location": null, "weight": 1.0}, {"source": "presentation_welcome_page_welcomepage", "target": "consumerwidget", "relation": "inherits", "confidence": "EXTRACTED", "confidence_score": 1.0, "source_file": "mobile/lib/features/subscription/presentation/welcome_page.dart", "source_location": null, "weight": 1.0}, {"source": "presentation_welcome_page_welcomepage", "target": "subscriptionprovider", "relation": "references", "confidence": "EXTRACTED", "confidence_score": 1.0, "source_file": "mobile/lib/features/subscription/presentation/welcome_page.dart", "source_location": null, "weight": 1.0, "context": "riverpod_reference"}, {"source": "home_khuzaymah_desktop_gym_pass_pro_gym_pass_pro_mobile_lib_features_subscription_presentation_welcome_page_dart", "target": "presentation_welcome_page_tiername", "relation": "defines", "confidence": "EXTRACTED", "confidence_score": 1.0, "source_file": "mobile/lib/features/subscription/presentation/welcome_page.dart", "source_location": null, "weight": 1.0}, {"source": "home_khuzaymah_desktop_gym_pass_pro_gym_pass_pro_mobile_lib_features_subscription_presentation_welcome_page_dart", "target": "presentation_welcome_page_build", "relation": "defines", "confidence": "EXTRACTED", "confidence_score": 1.0, "source_file": "mobile/lib/features/subscription/presentation/welcome_page.dart", "source_location": null, "weight": 1.0}, {"source": "presentation_welcome_page_build", "target": "subscriptionprovider", "relation": "references", "confidence": "EXTRACTED", "confidence_score": 1.0, "source_file": "mobile/lib/features/subscription/presentation/welcome_page.dart", "source_location": null, "weight": 1.0, "context": "riverpod_reference"}, {"source": "presentation_welcome_page_build", "target": "route_explore", "relation": "navigates", "confidence": "EXTRACTED", "confidence_score": 1.0, "source_file": "mobile/lib/features/subscription/presentation/welcome_page.dart", "source_location": null, "weight": 1.0, "context": "route_path"}, {"source": "presentation_welcome_page_build", "target": "route_home", "relation": "navigates", "confidence": "EXTRACTED", "confidence_score": 1.0, "source_file": "mobile/lib/features/subscription/presentation/welcome_page.dart", "source_location": null, "weight": 1.0, "context": "route_path"}, {"source": "home_khuzaymah_desktop_gym_pass_pro_gym_pass_pro_mobile_lib_features_subscription_presentation_welcome_page_dart", "target": "package_flutter_material_dart", "relation": "imports", "confidence": "EXTRACTED", "confidence_score": 1.0, "source_file": "mobile/lib/features/subscription/presentation/welcome_page.dart", "source_location": null, "weight": 1.0}, {"source": "home_khuzaymah_desktop_gym_pass_pro_gym_pass_pro_mobile_lib_features_subscription_presentation_welcome_page_dart", "target": "package_flutter_riverpod_flutter_riverpod_dart", "relation": "imports", "confidence": "EXTRACTED", "confidence_score": 1.0, "source_file": "mobile/lib/features/subscription/presentation/welcome_page.dart", "source_location": null, "weight": 1.0}, {"source": "home_khuzaymah_desktop_gym_pass_pro_gym_pass_pro_mobile_lib_features_subscription_presentation_welcome_page_dart", "target": "package_go_router_go_router_dart", "relation": "imports", "confidence": "EXTRACTED", "confidence_score": 1.0, "source_file": "mobile/lib/features/subscription/presentation/welcome_page.dart", "source_location": null, "weight": 1.0}, {"source": "home_khuzaymah_desktop_gym_pass_pro_gym_pass_pro_mobile_lib_features_subscription_presentation_welcome_page_dart", "target": "core_theme_gp_text_dart", "relation": "imports", "confidence": "EXTRACTED", "confidence_score": 1.0, "source_file": "mobile/lib/features/subscription/presentation/welcome_page.dart", "source_location": null, "weight": 1.0}, {"source": "home_khuzaymah_desktop_gym_pass_pro_gym_pass_pro_mobile_lib_features_subscription_presentation_welcome_page_dart", "target": "core_theme_gp_tokens_dart", "relation": "imports", "confidence": "EXTRACTED", "confidence_score": 1.0, "source_file": "mobile/lib/features/subscription/presentation/welcome_page.dart", "source_location": null, "weight": 1.0}, {"source": "home_khuzaymah_desktop_gym_pass_pro_gym_pass_pro_mobile_lib_features_subscription_presentation_welcome_page_dart", "target": "core_widgets_glow_dart", "relation": "imports", "confidence": "EXTRACTED", "confidence_score": 1.0, "source_file": "mobile/lib/features/subscription/presentation/welcome_page.dart", "source_location": null, "weight": 1.0}, {"source": "home_khuzaymah_desktop_gym_pass_pro_gym_pass_pro_mobile_lib_features_subscription_presentation_welcome_page_dart", "target": "core_widgets_overline_dart", "relation": "imports", "confidence": "EXTRACTED", "confidence_score": 1.0, "source_file": "mobile/lib/features/subscription/presentation/welcome_page.dart", "source_location": null, "weight": 1.0}, {"source": "home_khuzaymah_desktop_gym_pass_pro_gym_pass_pro_mobile_lib_features_subscription_presentation_welcome_page_dart", "target": "core_widgets_pill_button_dart", "relation": "imports", "confidence": "EXTRACTED", "confidence_score": 1.0, "source_file": "mobile/lib/features/subscription/presentation/welcome_page.dart", "source_location": null, "weight": 1.0}, {"source": "home_khuzaymah_desktop_gym_pass_pro_gym_pass_pro_mobile_lib_features_subscription_presentation_welcome_page_dart", "target": "l10n_app_localizations_dart", "relation": "imports", "confidence": "EXTRACTED", "confidence_score": 1.0, "source_file": "mobile/lib/features/subscription/presentation/welcome_page.dart", "source_location": null, "weight": 1.0}, {"source": "home_khuzaymah_desktop_gym_pass_pro_gym_pass_pro_mobile_lib_features_subscription_presentation_welcome_page_dart", "target": "data_subscription_state_dart", "relation": "imports", "confidence": "EXTRACTED", "confidence_score": 1.0, "source_file": "mobile/lib/features/subscription/presentation/welcome_page.dart", "source_location": null, "weight": 1.0}]}